<?xml version="1.0" encoding="UTF-8"?><record_update table="sysevent_register">
    <sysevent_register action="INSERT_OR_UPDATE">
        <caller_access/>
        <derived_priority/>
        <description>This file is deprecated and is no longer required.</description>
        <event_name>x_pd_integration.associate_services_DEPR</event_name>
        <fired_by/>
        <priority/>
        <queue/>
        <suffix>associate_services_DEPRECATED</suffix>
        <sys_class_name>sysevent_register</sys_class_name>
        <sys_created_by>PagerDuty_v8.0</sys_created_by>
        <sys_created_on>2020-05-27 15:53:33</sys_created_on>
        <sys_id>879d771d2f0510101bf7ffecf699b6d3</sys_id>
        <sys_mod_count>4</sys_mod_count>
        <sys_name>x_pd_integration.associate_services_DEPR</sys_name>
        <sys_package display_value="PagerDuty Incident Resolution Platform" source="x_pd_integration">39a9d9664f834e00dd657bb28110c77b</sys_package>
        <sys_policy/>
        <sys_scope display_value="PagerDuty Incident Resolution Platform">39a9d9664f834e00dd657bb28110c77b</sys_scope>
        <sys_update_name>sysevent_register_879d771d2f0510101bf7ffecf699b6d3</sys_update_name>
        <sys_updated_by>PagerDuty_v8.0</sys_updated_by>
        <sys_updated_on>2021-03-20 12:02:57</sys_updated_on>
        <table>cmdb_ci</table>
    </sysevent_register>
</record_update>
